gwtoolbox/EM_HE.py
gwtoolbox/EPTA.dat
gwtoolbox/ESS.py
gwtoolbox/HE_detectors.py
gwtoolbox/HE_models.py
gwtoolbox/IPTA.dat
gwtoolbox/IS_et.dat
gwtoolbox/IS_ligo.dat
gwtoolbox/NanoGrav.dat
gwtoolbox/PPTA.dat
gwtoolbox/__init__.py
gwtoolbox/constants.py
gwtoolbox/cosmology.py
gwtoolbox/detectors_earth.py
gwtoolbox/detectors_space.py
gwtoolbox/function_earth_fisher.py
gwtoolbox/functions_EMC.py
gwtoolbox/functions_earth.py
gwtoolbox/functions_pta.py
gwtoolbox/functions_space.py
gwtoolbox/parameters.py
gwtoolbox/plots.py
gwtoolbox/plotshtml.py
gwtoolbox/pta_pulsars.py
gwtoolbox/simulate_ligo.py
gwtoolbox/sources_kHz.py
gwtoolbox/sources_mHz.py
gwtoolbox/tools_EMC.py
gwtoolbox/tools_earth.py
gwtoolbox/tools_pta.py
gwtoolbox/tools_space.py
gwtoolbox/accessory/angles.dat
gwtoolbox/accessory/angles_more.dat
gwtoolbox/accessory/for_integral_et.txt
gwtoolbox/accessory/for_integral_et_BBH.txt
gwtoolbox/accessory/for_integral_et_BHNS.txt
gwtoolbox/accessory/for_integral_et_DNS.txt
gwtoolbox/accessory/for_integral_ligo.txt
gwtoolbox/accessory/for_integral_ligo_BBH.txt
gwtoolbox/accessory/for_integral_ligo_BHNS.txt
gwtoolbox/accessory/for_integral_ligo_DNS.txt
gwtoolbox/accessory/for_integral_med_BBH.txt
gwtoolbox/accessory/for_integral_med_BHNS.txt
gwtoolbox/accessory/for_integral_med_DNS.txt
gwtoolbox/data_detectors/ET.txt
gwtoolbox/data_detectors/KAGRA.txt
gwtoolbox/data_detectors/LISA.txt
gwtoolbox/data_detectors/aLIGO.txt
gwtoolbox/data_detectors/aLIGO_o4.txt
gwtoolbox/data_detectors/aVirgo.txt
gwtoolbox/data_detectors/ce1.txt
gwtoolbox/data_detectors/ce2.txt
gwtoolbox/data_detectors/o3_h1.txt
gwtoolbox/data_detectors/o3_l1.txt
gwtoolbox-1.1.dist-info/.SOURCES.txt.un~
gwtoolbox-1.1.dist-info/LICENSE.txt
gwtoolbox-1.1.dist-info/METADATA
gwtoolbox-1.1.dist-info/SOURCES.txt~
gwtoolbox-1.1.dist-info/WHEEL
gwtoolbox-1.1.dist-info/top_level.txt
gwtoolbox-1.1.dist-info/RECORD
