Metadata-Version: 2.1
Name: gwtoolbox
Version: 1.1
Summary: Gravitational Wave Tools
Home-page: https://gw-universe.org/
Author: UNKNOWN
Author-email: UNKNOWN
License: UNKNOWN
Platform: UNKNOWN
Requires-Dist: numpy
Requires-Dist: scipy
Requires-Dist: astropy
Requires-Dist: matplotlib
Requires-Dist: pykat
Requires-Dist: pycbc
